claripy/__init__.py
claripy/annotation.py
claripy/debug.py
claripy/errors.py
claripy/fp.py
claripy/operations.py
claripy/py.typed
claripy/simplifications.py
claripy/solvers.py
claripy/util.py
claripy/algorithm/__init__.py
claripy/algorithm/bool_check.py
claripy/algorithm/ite_relocation.py
claripy/algorithm/replace.py
claripy/algorithm/simplify.py
claripy/ast/__init__.py
claripy/ast/base.py
claripy/ast/bits.py
claripy/ast/bool.py
claripy/ast/bv.py
claripy/ast/bv.pyi
claripy/ast/fp.py
claripy/ast/strings.py
claripy/backends/__init__.py
claripy/backends/backend.py
claripy/backends/backend_any.py
claripy/backends/backend_z3.py
claripy/backends/backend_concrete/__init__.py
claripy/backends/backend_concrete/backend_concrete.py
claripy/backends/backend_concrete/bv.py
claripy/backends/backend_concrete/fp.py
claripy/backends/backend_concrete/strings.py
claripy/backends/backend_vsa/__init__.py
claripy/backends/backend_vsa/backend_vsa.py
claripy/backends/backend_vsa/balancer.py
claripy/backends/backend_vsa/bool_result.py
claripy/backends/backend_vsa/discrete_strided_interval_set.py
claripy/backends/backend_vsa/errors.py
claripy/backends/backend_vsa/strided_interval.py
claripy/backends/backend_vsa/valueset.py
claripy/backends/backend_vsa/warren_methods.py
claripy/frontend/__init__.py
claripy/frontend/composite_frontend.py
claripy/frontend/constrained_frontend.py
claripy/frontend/frontend.py
claripy/frontend/full_frontend.py
claripy/frontend/hybrid_frontend.py
claripy/frontend/light_frontend.py
claripy/frontend/replacement_frontend.py
claripy/frontend/mixin/__init__.py
claripy/frontend/mixin/composited_cache_mixin.py
claripy/frontend/mixin/concrete_handler_mixin.py
claripy/frontend/mixin/constraint_deduplicator_mixin.py
claripy/frontend/mixin/constraint_expansion_mixin.py
claripy/frontend/mixin/constraint_filter_mixin.py
claripy/frontend/mixin/eager_resolution_mixin.py
claripy/frontend/mixin/model_cache_mixin.py
claripy/frontend/mixin/sat_cache_mixin.py
claripy-9.2.193.dist-info/licenses/LICENSE
claripy-9.2.193.dist-info/METADATA
claripy-9.2.193.dist-info/WHEEL
claripy-9.2.193.dist-info/top_level.txt
claripy-9.2.193.dist-info/RECORD
